cli/__init__.py
cli/__main__.py
cli/main.py
cli/templates/readonly-user-template.sql.j2
cli/templates/readwrite-user-template.sql.j2
psql_script_generator-0.0.3.dist-info/METADATA
psql_script_generator-0.0.3.dist-info/WHEEL
psql_script_generator-0.0.3.dist-info/entry_points.txt
psql_script_generator-0.0.3.dist-info/licenses/LICENSE.txt
psql_script_generator-0.0.3.dist-info/RECORD
