Metadata-Version: 2.3
Name: psql-script-generator
Version: 0.0.3
Summary: It generates a SQL script based on a Jinja2 template, allowing you to automate the creation of a database, roles, and permissions.
Project-URL: Homepage, https://github.com/pledo/psql-script-generator
Project-URL: Repository, https://github.com/pledo/psql-script-generator.git
Author-email: Paulo Ledo <paulofledo@gmail.com>
Maintainer-email: Paulo Ledo <paulofledo@gmail.com>
License: MIT License
License-File: LICENSE.txt
Keywords: psql,readwrite,sql script
Classifier: Development Status :: 4 - Beta
Classifier: Programming Language :: Python
Requires-Python: >=3.8
Requires-Dist: jinja2
